semware/__init__.py
semware/cli.py
semware/config.py
semware/main.py
semware/api/__init__.py
semware/api/auth.py
semware/api/data.py
semware/api/search.py
semware/api/tables.py
semware/models/__init__.py
semware/models/requests.py
semware/models/schemas.py
semware/services/__init__.py
semware/services/embedding.py
semware/services/search.py
semware/services/vectordb.py
semware/utils/__init__.py
semware/utils/logging.py
semware/utils/tokenizer.py
semware-0.1.0.dist-info/METADATA
semware-0.1.0.dist-info/WHEEL
semware-0.1.0.dist-info/entry_points.txt
semware-0.1.0.dist-info/RECORD
