Metadata-Version: 2.4
Name: semware
Version: 0.1.0
Summary: Semantic search API server using vector databases and ML embeddings
Author: SemWare Team
License: MIT
Keywords: api,embeddings,machine-learning,semantic-search,vector-database
Classifier: Development Status :: 4 - Beta
Classifier: Intended Audience :: Developers
Classifier: License :: OSI Approved :: MIT License
Classifier: Programming Language :: Python :: 3
Classifier: Programming Language :: Python :: 3.11
Classifier: Programming Language :: Python :: 3.12
Classifier: Topic :: Scientific/Engineering :: Artificial Intelligence
Classifier: Topic :: Software Development :: Libraries :: Python Modules
Requires-Python: >=3.11
Requires-Dist: fastapi>=0.115.0
Requires-Dist: lancedb>=0.14.0
Requires-Dist: loguru>=0.7.2
Requires-Dist: numpy>=2.1.0
Requires-Dist: pandas>=2.2.0
Requires-Dist: pyarrow>=17.0.0
Requires-Dist: pydantic-settings>=2.10.1
Requires-Dist: pydantic>=2.9.0
Requires-Dist: python-dotenv>=1.0.0
Requires-Dist: python-multipart>=0.0.12
Requires-Dist: sentence-transformers>=3.1.0
Requires-Dist: tiktoken>=0.8.0
Requires-Dist: torch>=2.5.0
Requires-Dist: transformers>=4.45.0
Requires-Dist: uvicorn[standard]>=0.32.0
Provides-Extra: dev
Requires-Dist: black>=24.8.0; extra == 'dev'
Requires-Dist: httpx>=0.27.0; extra == 'dev'
Requires-Dist: mypy>=1.11.0; extra == 'dev'
Requires-Dist: pre-commit>=3.8.0; extra == 'dev'
Requires-Dist: pytest-asyncio>=0.24.0; extra == 'dev'
Requires-Dist: pytest-cov>=5.0.0; extra == 'dev'
Requires-Dist: pytest>=8.3.0; extra == 'dev'
Requires-Dist: ruff>=0.6.0; extra == 'dev'
